pypkgs_gs/__init__.py
pypkgs_gs/pypkgs_gs.py
pypkgs_gs-0.1.0.dist-info/LICENSE
pypkgs_gs-0.1.0.dist-info/WHEEL
pypkgs_gs-0.1.0.dist-info/METADATA
pypkgs_gs-0.1.0.dist-info/RECORD
